erdo/__init__.py
erdo/bot_permissions.py
erdo/cli_entry.py
erdo/formatting.py
erdo/install_cli.py
erdo/integrations.py
erdo/state.py
erdo/template.py
erdo/types.py
erdo/_generated/__init__.py
erdo/_generated/internal.py
erdo/_generated/internal_actions.py
erdo/_generated/parameters.py
erdo/_generated/secrets.py
erdo/_generated/template_functions.py
erdo/_generated/types.py
erdo/_generated/actions/__init__.py
erdo/_generated/actions/analysis.py
erdo/_generated/actions/bot.py
erdo/_generated/actions/codeexec.py
erdo/_generated/actions/llm.py
erdo/_generated/actions/memory.py
erdo/_generated/actions/pdfextractor.py
erdo/_generated/actions/resource_definitions.py
erdo/_generated/actions/sqlexec.py
erdo/_generated/actions/utils.py
erdo/_generated/actions/webparser.py
erdo/_generated/actions/websearch.py
erdo/_generated/condition/__init__.py
erdo/actions/__init__.py
erdo/conditions/__init__.py
erdo/config/__init__.py
erdo/config/config.py
erdo/invoke/__init__.py
erdo/invoke/client.py
erdo/invoke/invoke.py
erdo/sync/__init__.py
erdo/sync/client.py
erdo/sync/extractor.py
erdo/sync/sync.py
erdo/test/__init__.py
erdo/test/evaluate.py
erdo/test/runner.py
erdo-0.1.22.dist-info/METADATA
erdo-0.1.22.dist-info/WHEEL
erdo-0.1.22.dist-info/entry_points.txt
erdo-0.1.22.dist-info/licenses/LICENSE
erdo-0.1.22.dist-info/RECORD
